> Task :compileJava UP-TO-DATE
> Task :processResources UP-TO-DATE
> Task :classes UP-TO-DATE

> Task :run
DA ARGS:.temp
~~~~~~~~~~~~~~~~~~~~~~~~~~~~~~~~~~~~~~~~~~~~~~~~~~~~~~~~~~~~~~~~~~~~~~
~~~~~~~~~~~~~~~~~~~~~~~~~~~~~~~~~~~~~~~~~~~~~~~~~~~~~~~~~~~~~~~~~~~~~~
~~~~                                                              ~~~~
~~~~  COASTAL version coastal-test                                ~~~~
~~~~                                                              ~~~~
~~~~~~~~~~~~~~~~~~~~~~~~~~~~~~~~~~~~~~~~~~~~~~~~~~~~~~~~~~~~~~~~~~~~~~
~~~~~~~~~~~~~~~~~~~~~~~~~~~~~~~~~~~~~~~~~~~~~~~~~~~~~~~~~~~~~~~~~~~~~~
coastal.args = .temp
coastal.concrete.values = true
coastal.delegates = java.lang.String:za.ac.sun.cs.coastal.model.String@3e77a1ed
coastal.draw.paths = false
coastal.echooutput = true
coastal.limit.conjuncts = 0
coastal.limit.paths = 0
coastal.limit.runs = 0
coastal.limit.time = 0
coastal.main = examples.strings.DB
coastal.randomStrategy.seed = 987654321
coastal.strategy = za.ac.sun.cs.coastal.strategy.JAFLStrategy
coastal.targets = examples.strings
coastal.trace.all = false
coastal.triggers = za.ac.sun.cs.coastal.listener.control.StopController
----  starting dive 1  -----------------------------------------------
*** loading class examples.strings.DB, identified as target
visitCode()
visitLineNumber(line:6, label:L1489092624)
visitVarInsn(opcode:25, var:0)
visitMethodInsn(opcode:183, owner:java/lang/Object, name:<init>)
visitInsn(opcode:177)
visitEnd()
visitCode()
visitLineNumber(line:9, label:L252651381)
visitVarInsn(opcode:25, var:0)
visitInsn(opcode:3)
visitMethodInsn(opcode:182, owner:java/lang/String, name:charAt)
visitIntInsn(opcode:16, operand:100)
visitJumpInsn(opcode:160, label:L1514840818)
visitLineNumber(line:10, label:L1704064279)
visitVarInsn(opcode:25, var:0)
visitInsn(opcode:4)
visitMethodInsn(opcode:182, owner:java/lang/String, name:charAt)
visitIntInsn(opcode:16, operand:101)
visitJumpInsn(opcode:160, label:L878274034)
visitLineNumber(line:11, label:L1117509763)
visitVarInsn(opcode:25, var:0)
visitInsn(opcode:5)
visitMethodInsn(opcode:182, owner:java/lang/String, name:charAt)
visitIntInsn(opcode:16, operand:97)
visitJumpInsn(opcode:160, label:L878274034)
visitLineNumber(line:12, label:L1296674576)
visitVarInsn(opcode:25, var:0)
visitInsn(opcode:6)
visitMethodInsn(opcode:182, owner:java/lang/String, name:charAt)
visitIntInsn(opcode:16, operand:100)
visitJumpInsn(opcode:160, label:L878274034)
visitLineNumber(line:13, label:L664457955)
visitVarInsn(opcode:25, var:0)
visitInsn(opcode:7)
visitMethodInsn(opcode:182, owner:java/lang/String, name:charAt)
visitIntInsn(opcode:16, operand:98)
visitJumpInsn(opcode:160, label:L878274034)
visitLineNumber(line:14, label:L1477657879)
visitVarInsn(opcode:25, var:0)
visitInsn(opcode:8)
visitMethodInsn(opcode:182, owner:java/lang/String, name:charAt)
visitIntInsn(opcode:16, operand:101)
visitJumpInsn(opcode:160, label:L878274034)
visitLineNumber(line:15, label:L1146147158)
visitVarInsn(opcode:25, var:0)
visitIntInsn(opcode:16, operand:6)
visitMethodInsn(opcode:182, owner:java/lang/String, name:charAt)
visitIntInsn(opcode:16, operand:101)
visitJumpInsn(opcode:160, label:L878274034)
visitLineNumber(line:16, label:L1147258851)
visitVarInsn(opcode:25, var:0)
visitIntInsn(opcode:16, operand:7)
visitMethodInsn(opcode:182, owner:java/lang/String, name:charAt)
visitIntInsn(opcode:16, operand:102)
visitJumpInsn(opcode:160, label:L878274034)
visitLineNumber(line:17, label:L891095110)
visitInsn(opcode:4)
visitInsn(opcode:172)
visitLineNumber(line:25, label:L1514840818)
visitVarInsn(opcode:25, var:0)
visitInsn(opcode:3)
visitMethodInsn(opcode:182, owner:java/lang/String, name:charAt)
visitIntInsn(opcode:16, operand:102)
visitJumpInsn(opcode:160, label:L878274034)
visitLineNumber(line:26, label:L2011482127)
visitVarInsn(opcode:25, var:0)
visitInsn(opcode:4)
visitMethodInsn(opcode:182, owner:java/lang/String, name:charAt)
visitIntInsn(opcode:16, operand:117)
visitJumpInsn(opcode:160, label:L878274034)
visitLineNumber(line:27, label:L905735620)
visitVarInsn(opcode:25, var:0)
visitInsn(opcode:5)
visitMethodInsn(opcode:182, owner:java/lang/String, name:charAt)
visitIntInsn(opcode:16, operand:110)
visitJumpInsn(opcode:160, label:L878274034)
visitLineNumber(line:28, label:L2145970759)
visitVarInsn(opcode:25, var:0)
visitInsn(opcode:6)
visitMethodInsn(opcode:182, owner:java/lang/String, name:charAt)
visitIntInsn(opcode:16, operand:100)
visitJumpInsn(opcode:160, label:L878274034)
visitLineNumber(line:29, label:L577405636)
visitVarInsn(opcode:25, var:0)
visitInsn(opcode:7)
visitMethodInsn(opcode:182, owner:java/lang/String, name:charAt)
visitIntInsn(opcode:16, operand:97)
visitJumpInsn(opcode:160, label:L878274034)
visitLineNumber(line:30, label:L1931444790)
visitVarInsn(opcode:25, var:0)
visitInsn(opcode:8)
visitMethodInsn(opcode:182, owner:java/lang/String, name:charAt)
visitIntInsn(opcode:16, operand:122)
visitJumpInsn(opcode:160, label:L878274034)
visitLineNumber(line:31, label:L626742236)
visitVarInsn(opcode:25, var:0)
visitIntInsn(opcode:16, operand:6)
visitMethodInsn(opcode:182, owner:java/lang/String, name:charAt)
visitIntInsn(opcode:16, operand:101)
visitJumpInsn(opcode:160, label:L878274034)
visitLineNumber(line:32, label:L500772834)
visitVarInsn(opcode:25, var:0)
visitIntInsn(opcode:16, operand:7)
visitMethodInsn(opcode:182, owner:java/lang/String, name:charAt)
visitIntInsn(opcode:16, operand:100)
visitJumpInsn(opcode:160, label:L878274034)
visitLineNumber(line:33, label:L1800659519)
visitInsn(opcode:5)
visitInsn(opcode:172)
visitLineNumber(line:42, label:L878274034)
visitInsn(opcode:3)
visitInsn(opcode:172)
visitEnd()
visitCode()
visitLineNumber(line:46, label:L459848100)
visitTypeInsn(opcode:187, type:java/util/Scanner)
visitInsn(opcode:89)
visitTypeInsn(opcode:187, type:java/io/File)
visitInsn(opcode:89)
visitVarInsn(opcode:25, var:0)
visitInsn(opcode:3)
visitInsn(opcode:50)
visitMethodInsn(opcode:183, owner:java/io/File, name:<init>)
visitMethodInsn(opcode:183, owner:java/util/Scanner, name:<init>)
visitVarInsn(opcode:58, var:1)
visitLineNumber(line:47, label:L1335505684)
visitVarInsn(opcode:25, var:1)
visitMethodInsn(opcode:182, owner:java/util/Scanner, name:next)
visitVarInsn(opcode:58, var:2)
visitLineNumber(line:48, label:L992768706)
visitVarInsn(opcode:25, var:1)
visitMethodInsn(opcode:182, owner:java/util/Scanner, name:close)
visitLineNumber(line:49, label:L1226204845)
visitFieldInsn(opcode:178, owner:java/lang/System, name:out)
visitTypeInsn(opcode:187, type:java/lang/StringBuilder)
visitInsn(opcode:89)
visitMethodInsn(opcode:183, owner:java/lang/StringBuilder, name:<init>)
visitLdcInsn(value:Initial Word: )
visitMethodInsn(opcode:182, owner:java/lang/StringBuilder, name:append)
visitVarInsn(opcode:25, var:2)
visitMethodInsn(opcode:182, owner:java/lang/StringBuilder, name:append)
visitMethodInsn(opcode:182, owner:java/lang/StringBuilder, name:toString)
visitMethodInsn(opcode:182, owner:java/io/PrintStream, name:println)
visitLineNumber(line:50, label:L393040818)
visitVarInsn(opcode:25, var:2)
visitMethodInsn(opcode:184, owner:examples/strings/DB, name:analyse)
visitVarInsn(opcode:54, var:3)
visitLineNumber(line:51, label:L158453976)
visitInsn(opcode:177)
visitEnd()
*** instrumented examples.strings.DB: 1433 -> 4230 bytes
*** class examples.strings.DB instrumented
*** loading class java.lang.Object, uninstrumented
*** loading class java.lang.String, uninstrumented
*** loading class java.lang.Exception, uninstrumented
*** loading class za.ac.sun.cs.coastal.symbolic.SymbolicVM, uninstrumented
*** loading class java.util.Scanner, uninstrumented
*** loading class java.io.File, uninstrumented
*** loading class java.lang.System, uninstrumented
*** loading class java.lang.StringBuilder, uninstrumented
*** loading class java.io.PrintStream, uninstrumented
Initial Word: hello
>>> symbolic record mode switched on
--> st[] locals:{}
--> data:{}
### LINENUMBER 9
ALOAD 0
--> st[1] locals:{0=1}
--> data:{1/0=X_H_0, 1/1=X_H_1, 1/2=X_H_2, 1/3=X_H_3, 1/4=X_H_4, 1/length=5}
ICONST_0
--> st[1, 0] locals:{0=1}
--> data:{1/0=X_H_0, 1/1=X_H_1, 1/2=X_H_2, 1/3=X_H_3, 1/4=X_H_4, 1/length=5}
INVOKEVIRTUAL java/lang/String charAt (I)C
@@@ found delegate: charAt__I__C
--> st[X_H_0] locals:{0=1}
--> data:{1/0=X_H_0, 1/1=X_H_1, 1/2=X_H_2, 1/3=X_H_3, 1/4=X_H_4, 1/length=5}
BIPUSH 100
--> st[X_H_0, 100] locals:{0=1}
--> data:{1/0=X_H_0, 1/1=X_H_1, 1/2=X_H_2, 1/3=X_H_3, 1/4=X_H_4, 1/length=5}
IF_ICMPNE
>>> adding conjunct: X_H_0!=100
>>> spc is now: X_H_0!=100
--> st[] locals:{0=1}
--> data:{1/0=X_H_0, 1/1=X_H_1, 1/2=X_H_2, 1/3=X_H_3, 1/4=X_H_4, 1/length=5}
### LINENUMBER 25
ALOAD 0
--> st[1] locals:{0=1}
--> data:{1/0=X_H_0, 1/1=X_H_1, 1/2=X_H_2, 1/3=X_H_3, 1/4=X_H_4, 1/length=5}
ICONST_0
--> st[1, 0] locals:{0=1}
--> data:{1/0=X_H_0, 1/1=X_H_1, 1/2=X_H_2, 1/3=X_H_3, 1/4=X_H_4, 1/length=5}
INVOKEVIRTUAL java/lang/String charAt (I)C
@@@ found delegate: charAt__I__C
--> st[X_H_0] locals:{0=1}
--> data:{1/0=X_H_0, 1/1=X_H_1, 1/2=X_H_2, 1/3=X_H_3, 1/4=X_H_4, 1/length=5}
BIPUSH 102
--> st[X_H_0, 102] locals:{0=1}
--> data:{1/0=X_H_0, 1/1=X_H_1, 1/2=X_H_2, 1/3=X_H_3, 1/4=X_H_4, 1/length=5}
IF_ICMPNE
>>> adding conjunct: X_H_0!=102
>>> spc is now: (X_H_0!=102)&&(X_H_0!=100)
--> st[] locals:{0=1}
--> data:{1/0=X_H_0, 1/1=X_H_1, 1/2=X_H_2, 1/3=X_H_3, 1/4=X_H_4, 1/length=5}
### LINENUMBER 42
ICONST_0
--> st[0] locals:{0=1}
--> data:{1/0=X_H_0, 1/1=X_H_1, 1/2=X_H_2, 1/3=X_H_3, 1/4=X_H_4, 1/length=5}
IRETURN
>>> symbolic record mode switched off
--> data:{1/0=X_H_0, 1/1=X_H_1, 1/2=X_H_2, 1/3=X_H_3, 1/4=X_H_4, 1/length=5}
explored <11> (X_H_0!=102)&&(X_H_0!=100)
::: depth:2
::: insert(node:NUL, conjunct:X_H_0!=100, cur/depth:0/2)
::: create missing node #0
::: insert(node:NUL, conjunct:X_H_0!=102, cur/depth:1/2)
::: create missing node #1
::: create leaf
trying   <10> (X_H_0==102)&&(X_H_0!=100)
no model
(The spc is (X_H_0==102)&&(X_H_0!=100))
::: depth:2
::: insert(node:#0, conjunct:X_H_0!=100, cur/depth:0/2)
::: insert(node:#1, conjunct:X_H_0==102, cur/depth:1/2)
::: create infeasible node
::: setting #1 as fully explored
trying   <0> X_H_0==100
no model
(The spc is X_H_0==100)
::: depth:1
::: insert(node:#0, conjunct:X_H_0==100, cur/depth:0/1)
::: create infeasible node
::: setting #0 as fully explored
no further paths
Tree shape: (I(IL))
Printing input options
====  examples.strings.DB  ===========================================
------ <init> ------
    LDC 1
    LDC 1
    INVOKESTATIC za/ac/sun/cs/coastal/symbolic/SymbolicVM.startMethod (II)V
   L0
    LDC 0
    LDC 6
    INVOKESTATIC za/ac/sun/cs/coastal/symbolic/SymbolicVM.linenumber (II)V
    LINENUMBER 6 L0
    LDC 1
    LDC 25
    LDC 0
    INVOKESTATIC za/ac/sun/cs/coastal/symbolic/SymbolicVM.varInsn (III)V
    ALOAD 0
    LDC 2
    LDC 183
    LDC "java/lang/Object"
    LDC "<init>"
    LDC "()V"
    INVOKESTATIC za/ac/sun/cs/coastal/symbolic/SymbolicVM.methodInsn (IILjava/lang/String;Ljava/lang/String;Ljava/lang/String;)V
    INVOKESPECIAL java/lang/Object.<init> ()V
    LDC 3
    LDC 177
    INVOKESTATIC za/ac/sun/cs/coastal/symbolic/SymbolicVM.insn (II)V
    RETURN
   L1
    LOCALVARIABLE this Lexamples/strings/DB; L0 L1 0
    MAXSTACK = 1
    MAXLOCALS = 1
------ analyse ------
    INVOKESTATIC za/ac/sun/cs/coastal/symbolic/SymbolicVM.getRecordMode ()Z
    IFNE L0
    LDC 2
    INVOKESTATIC za/ac/sun/cs/coastal/symbolic/SymbolicVM.triggerMethod (I)V
    LDC 0
    LDC 0
    LDC 0
    ALOAD 0
    INVOKESTATIC za/ac/sun/cs/coastal/symbolic/SymbolicVM.getConcreteString (IIILjava/lang/String;)Ljava/lang/String;
    ASTORE 0
    GOTO L1
   L0
    LDC 2
   FRAME SAME
    LDC 1
    INVOKESTATIC za/ac/sun/cs/coastal/symbolic/SymbolicVM.startMethod (II)V
   L1
   FRAME SAME
   L2
    LDC 3
    LDC 9
    INVOKESTATIC za/ac/sun/cs/coastal/symbolic/SymbolicVM.linenumber (II)V
    LINENUMBER 9 L2
    LDC 4
    LDC 25
    LDC 0
    INVOKESTATIC za/ac/sun/cs/coastal/symbolic/SymbolicVM.varInsn (III)V
    ALOAD 0
    LDC 5
    LDC 3
    INVOKESTATIC za/ac/sun/cs/coastal/symbolic/SymbolicVM.insn (II)V
    ICONST_0
    LDC 6
    LDC 182
    LDC "java/lang/String"
    LDC "charAt"
    LDC "(I)C"
    INVOKESTATIC za/ac/sun/cs/coastal/symbolic/SymbolicVM.methodInsn (IILjava/lang/String;Ljava/lang/String;Ljava/lang/String;)V
    INVOKEVIRTUAL java/lang/String.charAt (I)C
    DUP
    INVOKESTATIC za/ac/sun/cs/coastal/symbolic/SymbolicVM.returnValue (C)V
    LDC 7
    LDC 16
    LDC 100
    INVOKESTATIC za/ac/sun/cs/coastal/symbolic/SymbolicVM.intInsn (III)V
    BIPUSH 100
    LDC 8
    LDC 160
    INVOKESTATIC za/ac/sun/cs/coastal/symbolic/SymbolicVM.jumpInsn (II)V
    IF_ICMPNE L3
    LDC 8
    LDC 160
    INVOKESTATIC za/ac/sun/cs/coastal/symbolic/SymbolicVM.postJumpInsn (II)V
   L4
    LDC 8
    LDC 10
    INVOKESTATIC za/ac/sun/cs/coastal/symbolic/SymbolicVM.linenumber (II)V
    LINENUMBER 10 L4
    LDC 9
    LDC 25
    LDC 0
    INVOKESTATIC za/ac/sun/cs/coastal/symbolic/SymbolicVM.varInsn (III)V
    ALOAD 0
    LDC 10
    LDC 4
    INVOKESTATIC za/ac/sun/cs/coastal/symbolic/SymbolicVM.insn (II)V
    ICONST_1
    LDC 11
    LDC 182
    LDC "java/lang/String"
    LDC "charAt"
    LDC "(I)C"
    INVOKESTATIC za/ac/sun/cs/coastal/symbolic/SymbolicVM.methodInsn (IILjava/lang/String;Ljava/lang/String;Ljava/lang/String;)V
    INVOKEVIRTUAL java/lang/String.charAt (I)C
    DUP
    INVOKESTATIC za/ac/sun/cs/coastal/symbolic/SymbolicVM.returnValue (C)V
    LDC 12
    LDC 16
    LDC 101
    INVOKESTATIC za/ac/sun/cs/coastal/symbolic/SymbolicVM.intInsn (III)V
    BIPUSH 101
    LDC 13
    LDC 160
    INVOKESTATIC za/ac/sun/cs/coastal/symbolic/SymbolicVM.jumpInsn (II)V
    IF_ICMPNE L5
    LDC 13
    LDC 160
    INVOKESTATIC za/ac/sun/cs/coastal/symbolic/SymbolicVM.postJumpInsn (II)V
   L6
    LDC 13
    LDC 11
    INVOKESTATIC za/ac/sun/cs/coastal/symbolic/SymbolicVM.linenumber (II)V
    LINENUMBER 11 L6
    LDC 14
    LDC 25
    LDC 0
    INVOKESTATIC za/ac/sun/cs/coastal/symbolic/SymbolicVM.varInsn (III)V
    ALOAD 0
    LDC 15
    LDC 5
    INVOKESTATIC za/ac/sun/cs/coastal/symbolic/SymbolicVM.insn (II)V
    ICONST_2
    LDC 16
    LDC 182
    LDC "java/lang/String"
    LDC "charAt"
    LDC "(I)C"
    INVOKESTATIC za/ac/sun/cs/coastal/symbolic/SymbolicVM.methodInsn (IILjava/lang/String;Ljava/lang/String;Ljava/lang/String;)V
    INVOKEVIRTUAL java/lang/String.charAt (I)C
    DUP
    INVOKESTATIC za/ac/sun/cs/coastal/symbolic/SymbolicVM.returnValue (C)V
    LDC 17
    LDC 16
    LDC 97
    INVOKESTATIC za/ac/sun/cs/coastal/symbolic/SymbolicVM.intInsn (III)V
    BIPUSH 97
    LDC 18
    LDC 160
    INVOKESTATIC za/ac/sun/cs/coastal/symbolic/SymbolicVM.jumpInsn (II)V
    IF_ICMPNE L5
    LDC 18
    LDC 160
    INVOKESTATIC za/ac/sun/cs/coastal/symbolic/SymbolicVM.postJumpInsn (II)V
   L7
    LDC 18
    LDC 12
    INVOKESTATIC za/ac/sun/cs/coastal/symbolic/SymbolicVM.linenumber (II)V
    LINENUMBER 12 L7
    LDC 19
    LDC 25
    LDC 0
    INVOKESTATIC za/ac/sun/cs/coastal/symbolic/SymbolicVM.varInsn (III)V
    ALOAD 0
    LDC 20
    LDC 6
    INVOKESTATIC za/ac/sun/cs/coastal/symbolic/SymbolicVM.insn (II)V
    ICONST_3
    LDC 21
    LDC 182
    LDC "java/lang/String"
    LDC "charAt"
    LDC "(I)C"
    INVOKESTATIC za/ac/sun/cs/coastal/symbolic/SymbolicVM.methodInsn (IILjava/lang/String;Ljava/lang/String;Ljava/lang/String;)V
    INVOKEVIRTUAL java/lang/String.charAt (I)C
    DUP
    INVOKESTATIC za/ac/sun/cs/coastal/symbolic/SymbolicVM.returnValue (C)V
    LDC 22
    LDC 16
    LDC 100
    INVOKESTATIC za/ac/sun/cs/coastal/symbolic/SymbolicVM.intInsn (III)V
    BIPUSH 100
    LDC 23
    LDC 160
    INVOKESTATIC za/ac/sun/cs/coastal/symbolic/SymbolicVM.jumpInsn (II)V
    IF_ICMPNE L5
    LDC 23
    LDC 160
    INVOKESTATIC za/ac/sun/cs/coastal/symbolic/SymbolicVM.postJumpInsn (II)V
   L8
    LDC 23
    LDC 13
    INVOKESTATIC za/ac/sun/cs/coastal/symbolic/SymbolicVM.linenumber (II)V
    LINENUMBER 13 L8
    LDC 24
    LDC 25
    LDC 0
    INVOKESTATIC za/ac/sun/cs/coastal/symbolic/SymbolicVM.varInsn (III)V
    ALOAD 0
    LDC 25
    LDC 7
    INVOKESTATIC za/ac/sun/cs/coastal/symbolic/SymbolicVM.insn (II)V
    ICONST_4
    LDC 26
    LDC 182
    LDC "java/lang/String"
    LDC "charAt"
    LDC "(I)C"
    INVOKESTATIC za/ac/sun/cs/coastal/symbolic/SymbolicVM.methodInsn (IILjava/lang/String;Ljava/lang/String;Ljava/lang/String;)V
    INVOKEVIRTUAL java/lang/String.charAt (I)C
    DUP
    INVOKESTATIC za/ac/sun/cs/coastal/symbolic/SymbolicVM.returnValue (C)V
    LDC 27
    LDC 16
    LDC 98
    INVOKESTATIC za/ac/sun/cs/coastal/symbolic/SymbolicVM.intInsn (III)V
    BIPUSH 98
    LDC 28
    LDC 160
    INVOKESTATIC za/ac/sun/cs/coastal/symbolic/SymbolicVM.jumpInsn (II)V
    IF_ICMPNE L5
    LDC 28
    LDC 160
    INVOKESTATIC za/ac/sun/cs/coastal/symbolic/SymbolicVM.postJumpInsn (II)V
   L9
    LDC 28
    LDC 14
    INVOKESTATIC za/ac/sun/cs/coastal/symbolic/SymbolicVM.linenumber (II)V
    LINENUMBER 14 L9
    LDC 29
    LDC 25
    LDC 0
    INVOKESTATIC za/ac/sun/cs/coastal/symbolic/SymbolicVM.varInsn (III)V
    ALOAD 0
    LDC 30
    LDC 8
    INVOKESTATIC za/ac/sun/cs/coastal/symbolic/SymbolicVM.insn (II)V
    ICONST_5
    LDC 31
    LDC 182
    LDC "java/lang/String"
    LDC "charAt"
    LDC "(I)C"
    INVOKESTATIC za/ac/sun/cs/coastal/symbolic/SymbolicVM.methodInsn (IILjava/lang/String;Ljava/lang/String;Ljava/lang/String;)V
    INVOKEVIRTUAL java/lang/String.charAt (I)C
    DUP
    INVOKESTATIC za/ac/sun/cs/coastal/symbolic/SymbolicVM.returnValue (C)V
    LDC 32
    LDC 16
    LDC 101
    INVOKESTATIC za/ac/sun/cs/coastal/symbolic/SymbolicVM.intInsn (III)V
    BIPUSH 101
    LDC 33
    LDC 160
    INVOKESTATIC za/ac/sun/cs/coastal/symbolic/SymbolicVM.jumpInsn (II)V
    IF_ICMPNE L5
    LDC 33
    LDC 160
    INVOKESTATIC za/ac/sun/cs/coastal/symbolic/SymbolicVM.postJumpInsn (II)V
   L10
    LDC 33
    LDC 15
    INVOKESTATIC za/ac/sun/cs/coastal/symbolic/SymbolicVM.linenumber (II)V
    LINENUMBER 15 L10
    LDC 34
    LDC 25
    LDC 0
    INVOKESTATIC za/ac/sun/cs/coastal/symbolic/SymbolicVM.varInsn (III)V
    ALOAD 0
    LDC 35
    LDC 16
    LDC 6
    INVOKESTATIC za/ac/sun/cs/coastal/symbolic/SymbolicVM.intInsn (III)V
    BIPUSH 6
    LDC 36
    LDC 182
    LDC "java/lang/String"
    LDC "charAt"
    LDC "(I)C"
    INVOKESTATIC za/ac/sun/cs/coastal/symbolic/SymbolicVM.methodInsn (IILjava/lang/String;Ljava/lang/String;Ljava/lang/String;)V
    INVOKEVIRTUAL java/lang/String.charAt (I)C
    DUP
    INVOKESTATIC za/ac/sun/cs/coastal/symbolic/SymbolicVM.returnValue (C)V
    LDC 37
    LDC 16
    LDC 101
    INVOKESTATIC za/ac/sun/cs/coastal/symbolic/SymbolicVM.intInsn (III)V
    BIPUSH 101
    LDC 38
    LDC 160
    INVOKESTATIC za/ac/sun/cs/coastal/symbolic/SymbolicVM.jumpInsn (II)V
    IF_ICMPNE L5
    LDC 38
    LDC 160
    INVOKESTATIC za/ac/sun/cs/coastal/symbolic/SymbolicVM.postJumpInsn (II)V
   L11
    LDC 38
    LDC 16
    INVOKESTATIC za/ac/sun/cs/coastal/symbolic/SymbolicVM.linenumber (II)V
    LINENUMBER 16 L11
    LDC 39
    LDC 25
    LDC 0
    INVOKESTATIC za/ac/sun/cs/coastal/symbolic/SymbolicVM.varInsn (III)V
    ALOAD 0
    LDC 40
    LDC 16
    LDC 7
    INVOKESTATIC za/ac/sun/cs/coastal/symbolic/SymbolicVM.intInsn (III)V
    BIPUSH 7
    LDC 41
    LDC 182
    LDC "java/lang/String"
    LDC "charAt"
    LDC "(I)C"
    INVOKESTATIC za/ac/sun/cs/coastal/symbolic/SymbolicVM.methodInsn (IILjava/lang/String;Ljava/lang/String;Ljava/lang/String;)V
    INVOKEVIRTUAL java/lang/String.charAt (I)C
    DUP
    INVOKESTATIC za/ac/sun/cs/coastal/symbolic/SymbolicVM.returnValue (C)V
    LDC 42
    LDC 16
    LDC 102
    INVOKESTATIC za/ac/sun/cs/coastal/symbolic/SymbolicVM.intInsn (III)V
    BIPUSH 102
    LDC 43
    LDC 160
    INVOKESTATIC za/ac/sun/cs/coastal/symbolic/SymbolicVM.jumpInsn (II)V
    IF_ICMPNE L5
    LDC 43
    LDC 160
    INVOKESTATIC za/ac/sun/cs/coastal/symbolic/SymbolicVM.postJumpInsn (II)V
   L12
    LDC 43
    LDC 17
    INVOKESTATIC za/ac/sun/cs/coastal/symbolic/SymbolicVM.linenumber (II)V
    LINENUMBER 17 L12
    LDC 44
    LDC 4
    INVOKESTATIC za/ac/sun/cs/coastal/symbolic/SymbolicVM.insn (II)V
    ICONST_1
    LDC 45
    LDC 172
    INVOKESTATIC za/ac/sun/cs/coastal/symbolic/SymbolicVM.insn (II)V
    IRETURN
   L3
    LDC 45
    LDC 25
    INVOKESTATIC za/ac/sun/cs/coastal/symbolic/SymbolicVM.linenumber (II)V
    LINENUMBER 25 L3
   FRAME SAME
    LDC 46
    LDC 25
    LDC 0
    INVOKESTATIC za/ac/sun/cs/coastal/symbolic/SymbolicVM.varInsn (III)V
    ALOAD 0
    LDC 47
    LDC 3
    INVOKESTATIC za/ac/sun/cs/coastal/symbolic/SymbolicVM.insn (II)V
    ICONST_0
    LDC 48
    LDC 182
    LDC "java/lang/String"
    LDC "charAt"
    LDC "(I)C"
    INVOKESTATIC za/ac/sun/cs/coastal/symbolic/SymbolicVM.methodInsn (IILjava/lang/String;Ljava/lang/String;Ljava/lang/String;)V
    INVOKEVIRTUAL java/lang/String.charAt (I)C
    DUP
    INVOKESTATIC za/ac/sun/cs/coastal/symbolic/SymbolicVM.returnValue (C)V
    LDC 49
    LDC 16
    LDC 102
    INVOKESTATIC za/ac/sun/cs/coastal/symbolic/SymbolicVM.intInsn (III)V
    BIPUSH 102
    LDC 50
    LDC 160
    INVOKESTATIC za/ac/sun/cs/coastal/symbolic/SymbolicVM.jumpInsn (II)V
    IF_ICMPNE L5
    LDC 50
    LDC 160
    INVOKESTATIC za/ac/sun/cs/coastal/symbolic/SymbolicVM.postJumpInsn (II)V
   L13
    LDC 50
    LDC 26
    INVOKESTATIC za/ac/sun/cs/coastal/symbolic/SymbolicVM.linenumber (II)V
    LINENUMBER 26 L13
    LDC 51
    LDC 25
    LDC 0
    INVOKESTATIC za/ac/sun/cs/coastal/symbolic/SymbolicVM.varInsn (III)V
    ALOAD 0
    LDC 52
    LDC 4
    INVOKESTATIC za/ac/sun/cs/coastal/symbolic/SymbolicVM.insn (II)V
    ICONST_1
    LDC 53
    LDC 182
    LDC "java/lang/String"
    LDC "charAt"
    LDC "(I)C"
    INVOKESTATIC za/ac/sun/cs/coastal/symbolic/SymbolicVM.methodInsn (IILjava/lang/String;Ljava/lang/String;Ljava/lang/String;)V
    INVOKEVIRTUAL java/lang/String.charAt (I)C
    DUP
    INVOKESTATIC za/ac/sun/cs/coastal/symbolic/SymbolicVM.returnValue (C)V
    LDC 54
    LDC 16
    LDC 117
    INVOKESTATIC za/ac/sun/cs/coastal/symbolic/SymbolicVM.intInsn (III)V
    BIPUSH 117
    LDC 55
    LDC 160
    INVOKESTATIC za/ac/sun/cs/coastal/symbolic/SymbolicVM.jumpInsn (II)V
    IF_ICMPNE L5
    LDC 55
    LDC 160
    INVOKESTATIC za/ac/sun/cs/coastal/symbolic/SymbolicVM.postJumpInsn (II)V
   L14
    LDC 55
    LDC 27
    INVOKESTATIC za/ac/sun/cs/coastal/symbolic/SymbolicVM.linenumber (II)V
    LINENUMBER 27 L14
    LDC 56
    LDC 25
    LDC 0
    INVOKESTATIC za/ac/sun/cs/coastal/symbolic/SymbolicVM.varInsn (III)V
    ALOAD 0
    LDC 57
    LDC 5
    INVOKESTATIC za/ac/sun/cs/coastal/symbolic/SymbolicVM.insn (II)V
    ICONST_2
    LDC 58
    LDC 182
    LDC "java/lang/String"
    LDC "charAt"
    LDC "(I)C"
    INVOKESTATIC za/ac/sun/cs/coastal/symbolic/SymbolicVM.methodInsn (IILjava/lang/String;Ljava/lang/String;Ljava/lang/String;)V
    INVOKEVIRTUAL java/lang/String.charAt (I)C
    DUP
    INVOKESTATIC za/ac/sun/cs/coastal/symbolic/SymbolicVM.returnValue (C)V
    LDC 59
    LDC 16
    LDC 110
    INVOKESTATIC za/ac/sun/cs/coastal/symbolic/SymbolicVM.intInsn (III)V
    BIPUSH 110
    LDC 60
    LDC 160
    INVOKESTATIC za/ac/sun/cs/coastal/symbolic/SymbolicVM.jumpInsn (II)V
    IF_ICMPNE L5
    LDC 60
    LDC 160
    INVOKESTATIC za/ac/sun/cs/coastal/symbolic/SymbolicVM.postJumpInsn (II)V
   L15
    LDC 60
    LDC 28
    INVOKESTATIC za/ac/sun/cs/coastal/symbolic/SymbolicVM.linenumber (II)V
    LINENUMBER 28 L15
    LDC 61
    LDC 25
    LDC 0
    INVOKESTATIC za/ac/sun/cs/coastal/symbolic/SymbolicVM.varInsn (III)V
    ALOAD 0
    LDC 62
    LDC 6
    INVOKESTATIC za/ac/sun/cs/coastal/symbolic/SymbolicVM.insn (II)V
    ICONST_3
    LDC 63
    LDC 182
    LDC "java/lang/String"
    LDC "charAt"
    LDC "(I)C"
    INVOKESTATIC za/ac/sun/cs/coastal/symbolic/SymbolicVM.methodInsn (IILjava/lang/String;Ljava/lang/String;Ljava/lang/String;)V
    INVOKEVIRTUAL java/lang/String.charAt (I)C
    DUP
    INVOKESTATIC za/ac/sun/cs/coastal/symbolic/SymbolicVM.returnValue (C)V
    LDC 64
    LDC 16
    LDC 100
    INVOKESTATIC za/ac/sun/cs/coastal/symbolic/SymbolicVM.intInsn (III)V
    BIPUSH 100
    LDC 65
    LDC 160
    INVOKESTATIC za/ac/sun/cs/coastal/symbolic/SymbolicVM.jumpInsn (II)V
    IF_ICMPNE L5
    LDC 65
    LDC 160
    INVOKESTATIC za/ac/sun/cs/coastal/symbolic/SymbolicVM.postJumpInsn (II)V
   L16
    LDC 65
    LDC 29
    INVOKESTATIC za/ac/sun/cs/coastal/symbolic/SymbolicVM.linenumber (II)V
    LINENUMBER 29 L16
    LDC 66
    LDC 25
    LDC 0
    INVOKESTATIC za/ac/sun/cs/coastal/symbolic/SymbolicVM.varInsn (III)V
    ALOAD 0
    LDC 67
    LDC 7
    INVOKESTATIC za/ac/sun/cs/coastal/symbolic/SymbolicVM.insn (II)V
    ICONST_4
    LDC 68
    LDC 182
    LDC "java/lang/String"
    LDC "charAt"
    LDC "(I)C"
    INVOKESTATIC za/ac/sun/cs/coastal/symbolic/SymbolicVM.methodInsn (IILjava/lang/String;Ljava/lang/String;Ljava/lang/String;)V
    INVOKEVIRTUAL java/lang/String.charAt (I)C
    DUP
    INVOKESTATIC za/ac/sun/cs/coastal/symbolic/SymbolicVM.returnValue (C)V
    LDC 69
    LDC 16
    LDC 97
    INVOKESTATIC za/ac/sun/cs/coastal/symbolic/SymbolicVM.intInsn (III)V
    BIPUSH 97
    LDC 70
    LDC 160
    INVOKESTATIC za/ac/sun/cs/coastal/symbolic/SymbolicVM.jumpInsn (II)V
    IF_ICMPNE L5
    LDC 70
    LDC 160
    INVOKESTATIC za/ac/sun/cs/coastal/symbolic/SymbolicVM.postJumpInsn (II)V
   L17
    LDC 70
    LDC 30
    INVOKESTATIC za/ac/sun/cs/coastal/symbolic/SymbolicVM.linenumber (II)V
    LINENUMBER 30 L17
    LDC 71
    LDC 25
    LDC 0
    INVOKESTATIC za/ac/sun/cs/coastal/symbolic/SymbolicVM.varInsn (III)V
    ALOAD 0
    LDC 72
    LDC 8
    INVOKESTATIC za/ac/sun/cs/coastal/symbolic/SymbolicVM.insn (II)V
    ICONST_5
    LDC 73
    LDC 182
    LDC "java/lang/String"
    LDC "charAt"
    LDC "(I)C"
    INVOKESTATIC za/ac/sun/cs/coastal/symbolic/SymbolicVM.methodInsn (IILjava/lang/String;Ljava/lang/String;Ljava/lang/String;)V
    INVOKEVIRTUAL java/lang/String.charAt (I)C
    DUP
    INVOKESTATIC za/ac/sun/cs/coastal/symbolic/SymbolicVM.returnValue (C)V
    LDC 74
    LDC 16
    LDC 122
    INVOKESTATIC za/ac/sun/cs/coastal/symbolic/SymbolicVM.intInsn (III)V
    BIPUSH 122
    LDC 75
    LDC 160
    INVOKESTATIC za/ac/sun/cs/coastal/symbolic/SymbolicVM.jumpInsn (II)V
    IF_ICMPNE L5
    LDC 75
    LDC 160
    INVOKESTATIC za/ac/sun/cs/coastal/symbolic/SymbolicVM.postJumpInsn (II)V
   L18
    LDC 75
    LDC 31
    INVOKESTATIC za/ac/sun/cs/coastal/symbolic/SymbolicVM.linenumber (II)V
    LINENUMBER 31 L18
    LDC 76
    LDC 25
    LDC 0
    INVOKESTATIC za/ac/sun/cs/coastal/symbolic/SymbolicVM.varInsn (III)V
    ALOAD 0
    LDC 77
    LDC 16
    LDC 6
    INVOKESTATIC za/ac/sun/cs/coastal/symbolic/SymbolicVM.intInsn (III)V
    BIPUSH 6
    LDC 78
    LDC 182
    LDC "java/lang/String"
    LDC "charAt"
    LDC "(I)C"
    INVOKESTATIC za/ac/sun/cs/coastal/symbolic/SymbolicVM.methodInsn (IILjava/lang/String;Ljava/lang/String;Ljava/lang/String;)V
    INVOKEVIRTUAL java/lang/String.charAt (I)C
    DUP
    INVOKESTATIC za/ac/sun/cs/coastal/symbolic/SymbolicVM.returnValue (C)V
    LDC 79
    LDC 16
    LDC 101
    INVOKESTATIC za/ac/sun/cs/coastal/symbolic/SymbolicVM.intInsn (III)V
    BIPUSH 101
    LDC 80
    LDC 160
    INVOKESTATIC za/ac/sun/cs/coastal/symbolic/SymbolicVM.jumpInsn (II)V
    IF_ICMPNE L5
    LDC 80
    LDC 160
    INVOKESTATIC za/ac/sun/cs/coastal/symbolic/SymbolicVM.postJumpInsn (II)V
   L19
    LDC 80
    LDC 32
    INVOKESTATIC za/ac/sun/cs/coastal/symbolic/SymbolicVM.linenumber (II)V
    LINENUMBER 32 L19
    LDC 81
    LDC 25
    LDC 0
    INVOKESTATIC za/ac/sun/cs/coastal/symbolic/SymbolicVM.varInsn (III)V
    ALOAD 0
    LDC 82
    LDC 16
    LDC 7
    INVOKESTATIC za/ac/sun/cs/coastal/symbolic/SymbolicVM.intInsn (III)V
    BIPUSH 7
    LDC 83
    LDC 182
    LDC "java/lang/String"
    LDC "charAt"
    LDC "(I)C"
    INVOKESTATIC za/ac/sun/cs/coastal/symbolic/SymbolicVM.methodInsn (IILjava/lang/String;Ljava/lang/String;Ljava/lang/String;)V
    INVOKEVIRTUAL java/lang/String.charAt (I)C
    DUP
    INVOKESTATIC za/ac/sun/cs/coastal/symbolic/SymbolicVM.returnValue (C)V
    LDC 84
    LDC 16
    LDC 100
    INVOKESTATIC za/ac/sun/cs/coastal/symbolic/SymbolicVM.intInsn (III)V
    BIPUSH 100
    LDC 85
    LDC 160
    INVOKESTATIC za/ac/sun/cs/coastal/symbolic/SymbolicVM.jumpInsn (II)V
    IF_ICMPNE L5
    LDC 85
    LDC 160
    INVOKESTATIC za/ac/sun/cs/coastal/symbolic/SymbolicVM.postJumpInsn (II)V
   L20
    LDC 85
    LDC 33
    INVOKESTATIC za/ac/sun/cs/coastal/symbolic/SymbolicVM.linenumber (II)V
    LINENUMBER 33 L20
    LDC 86
    LDC 5
    INVOKESTATIC za/ac/sun/cs/coastal/symbolic/SymbolicVM.insn (II)V
    ICONST_2
    LDC 87
    LDC 172
    INVOKESTATIC za/ac/sun/cs/coastal/symbolic/SymbolicVM.insn (II)V
    IRETURN
   L5
    LDC 87
    LDC 42
    INVOKESTATIC za/ac/sun/cs/coastal/symbolic/SymbolicVM.linenumber (II)V
    LINENUMBER 42 L5
   FRAME SAME
    LDC 88
    LDC 3
    INVOKESTATIC za/ac/sun/cs/coastal/symbolic/SymbolicVM.insn (II)V
    ICONST_0
    LDC 89
    LDC 172
    INVOKESTATIC za/ac/sun/cs/coastal/symbolic/SymbolicVM.insn (II)V
    IRETURN
   L21
    LOCALVARIABLE word Ljava/lang/String; L2 L21 0
    MAXSTACK = 2
    MAXLOCALS = 1
------ main ------
    LDC 3
    LDC 1
    INVOKESTATIC za/ac/sun/cs/coastal/symbolic/SymbolicVM.startMethod (II)V
   L0
    LDC 89
    LDC 46
    INVOKESTATIC za/ac/sun/cs/coastal/symbolic/SymbolicVM.linenumber (II)V
    LINENUMBER 46 L0
    LDC 90
    LDC 187
    INVOKESTATIC za/ac/sun/cs/coastal/symbolic/SymbolicVM.typeInsn (II)V
    NEW java/util/Scanner
    LDC 91
    LDC 89
    INVOKESTATIC za/ac/sun/cs/coastal/symbolic/SymbolicVM.insn (II)V
    DUP
    LDC 92
    LDC 187
    INVOKESTATIC za/ac/sun/cs/coastal/symbolic/SymbolicVM.typeInsn (II)V
    NEW java/io/File
    LDC 93
    LDC 89
    INVOKESTATIC za/ac/sun/cs/coastal/symbolic/SymbolicVM.insn (II)V
    DUP
    LDC 94
    LDC 25
    LDC 0
    INVOKESTATIC za/ac/sun/cs/coastal/symbolic/SymbolicVM.varInsn (III)V
    ALOAD 0
    LDC 95
    LDC 3
    INVOKESTATIC za/ac/sun/cs/coastal/symbolic/SymbolicVM.insn (II)V
    ICONST_0
    LDC 96
    LDC 50
    INVOKESTATIC za/ac/sun/cs/coastal/symbolic/SymbolicVM.insn (II)V
    AALOAD
    LDC 97
    LDC 183
    LDC "java/io/File"
    LDC "<init>"
    LDC "(Ljava/lang/String;)V"
    INVOKESTATIC za/ac/sun/cs/coastal/symbolic/SymbolicVM.methodInsn (IILjava/lang/String;Ljava/lang/String;Ljava/lang/String;)V
    INVOKESPECIAL java/io/File.<init> (Ljava/lang/String;)V
    LDC 98
    LDC 183
    LDC "java/util/Scanner"
    LDC "<init>"
    LDC "(Ljava/io/File;)V"
    INVOKESTATIC za/ac/sun/cs/coastal/symbolic/SymbolicVM.methodInsn (IILjava/lang/String;Ljava/lang/String;Ljava/lang/String;)V
    INVOKESPECIAL java/util/Scanner.<init> (Ljava/io/File;)V
    LDC 99
    LDC 58
    LDC 1
    INVOKESTATIC za/ac/sun/cs/coastal/symbolic/SymbolicVM.varInsn (III)V
    ASTORE 1
   L1
    LDC 99
    LDC 47
    INVOKESTATIC za/ac/sun/cs/coastal/symbolic/SymbolicVM.linenumber (II)V
    LINENUMBER 47 L1
    LDC 100
    LDC 25
    LDC 1
    INVOKESTATIC za/ac/sun/cs/coastal/symbolic/SymbolicVM.varInsn (III)V
    ALOAD 1
    LDC 101
    LDC 182
    LDC "java/util/Scanner"
    LDC "next"
    LDC "()Ljava/lang/String;"
    INVOKESTATIC za/ac/sun/cs/coastal/symbolic/SymbolicVM.methodInsn (IILjava/lang/String;Ljava/lang/String;Ljava/lang/String;)V
    INVOKEVIRTUAL java/util/Scanner.next ()Ljava/lang/String;
    LDC 102
    LDC 58
    LDC 2
    INVOKESTATIC za/ac/sun/cs/coastal/symbolic/SymbolicVM.varInsn (III)V
    ASTORE 2
   L2
    LDC 102
    LDC 48
    INVOKESTATIC za/ac/sun/cs/coastal/symbolic/SymbolicVM.linenumber (II)V
    LINENUMBER 48 L2
    LDC 103
    LDC 25
    LDC 1
    INVOKESTATIC za/ac/sun/cs/coastal/symbolic/SymbolicVM.varInsn (III)V
    ALOAD 1
    LDC 104
    LDC 182
    LDC "java/util/Scanner"
    LDC "close"
    LDC "()V"
    INVOKESTATIC za/ac/sun/cs/coastal/symbolic/SymbolicVM.methodInsn (IILjava/lang/String;Ljava/lang/String;Ljava/lang/String;)V
    INVOKEVIRTUAL java/util/Scanner.close ()V
   L3
    LDC 104
    LDC 49
    INVOKESTATIC za/ac/sun/cs/coastal/symbolic/SymbolicVM.linenumber (II)V
    LINENUMBER 49 L3
    LDC 105
    LDC 178
    LDC "java/lang/System"
    LDC "out"
    LDC "Ljava/io/PrintStream;"
    INVOKESTATIC za/ac/sun/cs/coastal/symbolic/SymbolicVM.fieldInsn (IILjava/lang/String;Ljava/lang/String;Ljava/lang/String;)V
    GETSTATIC java/lang/System.out : Ljava/io/PrintStream;
    LDC 106
    LDC 187
    INVOKESTATIC za/ac/sun/cs/coastal/symbolic/SymbolicVM.typeInsn (II)V
    NEW java/lang/StringBuilder
    LDC 107
    LDC 89
    INVOKESTATIC za/ac/sun/cs/coastal/symbolic/SymbolicVM.insn (II)V
    DUP
    LDC 108
    LDC 183
    LDC "java/lang/StringBuilder"
    LDC "<init>"
    LDC "()V"
    INVOKESTATIC za/ac/sun/cs/coastal/symbolic/SymbolicVM.methodInsn (IILjava/lang/String;Ljava/lang/String;Ljava/lang/String;)V
    INVOKESPECIAL java/lang/StringBuilder.<init> ()V
    LDC 109
    LDC 18
    LDC "Initial Word: "
    INVOKESTATIC za/ac/sun/cs/coastal/symbolic/SymbolicVM.ldcInsn (IILjava/lang/Object;)V
    LDC "Initial Word: "
    LDC 110
    LDC 182
    LDC "java/lang/StringBuilder"
    LDC "append"
    LDC "(Ljava/lang/String;)Ljava/lang/StringBuilder;"
    INVOKESTATIC za/ac/sun/cs/coastal/symbolic/SymbolicVM.methodInsn (IILjava/lang/String;Ljava/lang/String;Ljava/lang/String;)V
    INVOKEVIRTUAL java/lang/StringBuilder.append (Ljava/lang/String;)Ljava/lang/StringBuilder;
    LDC 111
    LDC 25
    LDC 2
    INVOKESTATIC za/ac/sun/cs/coastal/symbolic/SymbolicVM.varInsn (III)V
    ALOAD 2
    LDC 112
    LDC 182
    LDC "java/lang/StringBuilder"
    LDC "append"
    LDC "(Ljava/lang/String;)Ljava/lang/StringBuilder;"
    INVOKESTATIC za/ac/sun/cs/coastal/symbolic/SymbolicVM.methodInsn (IILjava/lang/String;Ljava/lang/String;Ljava/lang/String;)V
    INVOKEVIRTUAL java/lang/StringBuilder.append (Ljava/lang/String;)Ljava/lang/StringBuilder;
    LDC 113
    LDC 182
    LDC "java/lang/StringBuilder"
    LDC "toString"
    LDC "()Ljava/lang/String;"
    INVOKESTATIC za/ac/sun/cs/coastal/symbolic/SymbolicVM.methodInsn (IILjava/lang/String;Ljava/lang/String;Ljava/lang/String;)V
    INVOKEVIRTUAL java/lang/StringBuilder.toString ()Ljava/lang/String;
    LDC 114
    LDC 182
    LDC "java/io/PrintStream"
    LDC "println"
    LDC "(Ljava/lang/String;)V"
    INVOKESTATIC za/ac/sun/cs/coastal/symbolic/SymbolicVM.methodInsn (IILjava/lang/String;Ljava/lang/String;Ljava/lang/String;)V
    INVOKEVIRTUAL java/io/PrintStream.println (Ljava/lang/String;)V
   L4
    LDC 114
    LDC 50
    INVOKESTATIC za/ac/sun/cs/coastal/symbolic/SymbolicVM.linenumber (II)V
    LINENUMBER 50 L4
    LDC 115
    LDC 25
    LDC 2
    INVOKESTATIC za/ac/sun/cs/coastal/symbolic/SymbolicVM.varInsn (III)V
    ALOAD 2
    LDC 116
    LDC 184
    LDC "examples/strings/DB"
    LDC "analyse"
    LDC "(Ljava/lang/String;)I"
    INVOKESTATIC za/ac/sun/cs/coastal/symbolic/SymbolicVM.methodInsn (IILjava/lang/String;Ljava/lang/String;Ljava/lang/String;)V
    INVOKESTATIC examples/strings/DB.analyse (Ljava/lang/String;)I
    LDC 117
    LDC 54
    LDC 3
    INVOKESTATIC za/ac/sun/cs/coastal/symbolic/SymbolicVM.varInsn (III)V
    ISTORE 3
   L5
    LDC 117
    LDC 51
    INVOKESTATIC za/ac/sun/cs/coastal/symbolic/SymbolicVM.linenumber (II)V
    LINENUMBER 51 L5
    LDC 118
    LDC 177
    INVOKESTATIC za/ac/sun/cs/coastal/symbolic/SymbolicVM.insn (II)V
    RETURN
   L6
    LOCALVARIABLE args [Ljava/lang/String; L0 L6 0
    LOCALVARIABLE sc Ljava/util/Scanner; L1 L6 1
    LOCALVARIABLE word Ljava/lang/String; L2 L6 2
    LOCALVARIABLE r I L5 L6 3
    MAXSTACK = 6
    MAXLOCALS = 4
====  Instrumentation  ===============================================
  Class load requests: 10
  Cache hits: 0
  Classes instrumented: 1
  Pre-instrumented size: 1433
  Post-instrumented size: 4230
  Load time: 29
  Instrumentation time: 29
====  Dive  ==========================================================
  Runs: 1
  Overall dive time: 39
====  COASTAL  =======================================================
  Started: Sun 2 Sep 2018 14:40:13
  Stopped: Sun 2 Sep 2018 14:40:13
  Overall time: 67
====  RandomStrategy  ================================================
  Inserted paths: 3
  Revisited paths: 0
  Infeasible paths: 2
  Solver time: 7
  Path tree time: 1
  Model extraction time: 0
  Overall strategy time: 8
@@@@@@@@@@@@@@@@@@@@@@@@@@@@@@@@@@@@@@@@@@@@@@@@@@@@@@@@@@@@@@@@@@@@@@
@@@@@@@@@@@@@@@@@@@@@@@@@@@@@@@@@@@@@@@@@@@@@@@@@@@@@@@@@@@@@@@@@@@@@@
@@@@                                                              @@@@
@@@@  ONLY A SINGLE RUN EXECUTED                                  @@@@
@@@@  CHECK YOUR SETTINGS -- THERE MIGHT BE A PROBLEM SOMEWHERE   @@@@
@@@@                                                              @@@@
@@@@@@@@@@@@@@@@@@@@@@@@@@@@@@@@@@@@@@@@@@@@@@@@@@@@@@@@@@@@@@@@@@@@@@
@@@@@@@@@@@@@@@@@@@@@@@@@@@@@@@@@@@@@@@@@@@@@@@@@@@@@@@@@@@@@@@@@@@@@@
~~~~~~~~~~~~~~~~~~~~~~~~~~~~~~~~~~~~~~~~~~~~~~~~~~~~~~~~~~~~~~~~~~~~~~
~~~~~~~~~~~~~~~~~~~~~~~~~~~~~~~~~~~~~~~~~~~~~~~~~~~~~~~~~~~~~~~~~~~~~~
~~~~                                                              ~~~~
~~~~  COASTAL DONE                                                ~~~~
~~~~                                                              ~~~~
~~~~~~~~~~~~~~~~~~~~~~~~~~~~~~~~~~~~~~~~~~~~~~~~~~~~~~~~~~~~~~~~~~~~~~
~~~~~~~~~~~~~~~~~~~~~~~~~~~~~~~~~~~~~~~~~~~~~~~~~~~~~~~~~~~~~~~~~~~~~~
COASTAL RAN SUCCESSFULLY
Initial Word: hello
